cpknextgen/__init__.py
cpknextgen/__main__.py
cpknextgen/capability_index.py
cpknextgen/custom_exceptions.py
cpknextgen/graphics.py
cpknextgen/transformation.py
cpknextgen/normal_mixture/__init__.py
cpknextgen/normal_mixture/inference.py
cpknextgen/normal_mixture/parameters_estimate.py
cpknextgen-2.0.0.dist-info/METADATA
cpknextgen-2.0.0.dist-info/WHEEL
cpknextgen-2.0.0.dist-info/licenses/LICENSE
cpknextgen-2.0.0.dist-info/RECORD
