Metadata-Version: 2.4
Name: cpknextgen
Version: 2.0.0
Summary: Cpk NextGen
Project-URL: Homepage, https://github.com/diribet/cpknextgen
Project-URL: Issues, https://github.com/diribet/cpknextgen/issues
Author-email: Stanislav Král <stanislav.kral@diribet.cz>, Jaroslav Staněk <jaroslav.stanek@diribet.cz>, Helena Paulasová <helena.paulasova@diribet.cz>, Vlastimil Dolejš <vlastimil.dolejs@diribet.cz>
License: MIT License
License-File: LICENSE
Keywords: Cp,Cpk,Process capability
Classifier: Intended Audience :: Manufacturing
Classifier: License :: OSI Approved :: MIT License
Classifier: Operating System :: OS Independent
Classifier: Programming Language :: Python :: 3
Requires-Python: >=3.10
Requires-Dist: numba>=0.55.0
Requires-Dist: numpy<2.4,>=1.21
Requires-Dist: scikit-learn>=1.0
Requires-Dist: scipy<1.16,>=1.10
Provides-Extra: test
Requires-Dist: pytest-sugar>=0.9; extra == 'test'
Requires-Dist: pytest>=7; extra == 'test'
